aws_cli_adfs/__init__.py
aws_cli_adfs/cli.py
aws_cli_adfs/constants.py
aws_cli_adfs/exceptions.py
aws_cli_adfs/log.py
aws_cli_adfs/login.py
aws_cli_adfs/utils.py
awscli_adfs-0.1.6.dist-info/METADATA
awscli_adfs-0.1.6.dist-info/WHEEL
awscli_adfs-0.1.6.dist-info/entry_points.txt
awscli_adfs-0.1.6.dist-info/top_level.txt
awscli_adfs-0.1.6.dist-info/RECORD
