Metadata-Version: 2.1
Name: awscli-adfs
Version: 0.1.6
Summary: Login to AWS CLI using Active Directory Federation Services.
Home-page: https://github.com/duckgogo/aws-cli-adfs
Author: duckgogo
Author-email: zeng.jianxin@foxmail.com
License: UNKNOWN
Platform: UNKNOWN
Requires-Python: >=3.5
Requires-Dist: awscli
Requires-Dist: beautifulsoup4
Requires-Dist: boto
Requires-Dist: Click
Requires-Dist: configparser
Requires-Dist: requests
Requires-Dist: toml
